{
	"path": "assets/img/terrain.png",
	"datas": [
		{
			"name": "red_grass",
			"position": {
				"x": 0,
				"y": 0
			}
		},
		{
			"name": "blue_rock",
			"position": {
				"x": 0,
				"y": 1
			}
		},
		{
			"name": "tree_trunk",
			"position": {
				"x": 0,
				"y": 2
			}
		},
		{
			"name": "tree_leafs",
			"position": {
				"x": 3,
				"y": 2
			}
		},
		{
			"name": "sand_rock",
			"position": {
				"x": 3,
				"y": 0
			}
		},
		{
			"name": "blue_built_rock",
			"position": {
				"x": 3,
				"y": 1
			}
		}
	]
}